gamspec/Operator.py
gamspec/PeakRegion.py
gamspec/Spectrum.py
gamspec/__init__.py
gamspec/plot_settings.py
gamspec/utils.py
gamspec/operators/AreaCalculator.py
gamspec/operators/BasicOperator.py
gamspec/operators/OtherOperator.py
gamspec/operators/PeakSearcher.py
gamspec/operators/Smoother.py
gamspec/operators/__init__.py
gamspec-0.1.1.dist-info/LICENSE
gamspec-0.1.1.dist-info/METADATA
gamspec-0.1.1.dist-info/WHEEL
gamspec-0.1.1.dist-info/top_level.txt
gamspec-0.1.1.dist-info/RECORD
