Metadata-Version: 2.1
Name: gamspec
Version: 0.1.1
Summary: Gamut is a Python package for the analysis of 1-d gamma spectrum.
Home-page: https://github.com/thu-inet/Gamut
Author: THU-RSAG
Author-email: z-wj21@mails.tsinghua.edu.cn
License: UNKNOWN
Platform: UNKNOWN
Classifier: Development Status :: 3 - Alpha
Classifier: Programming Language :: Python :: 3
Classifier: License :: OSI Approved :: MIT License
Classifier: Operating System :: OS Independent
License-File: LICENSE
Requires-Dist: numpy (>=1.25.0)
Requires-Dist: matplotlib (>=3.7.0)
